spring_equations/__init__.py
spring_equations/harmonic_oscillator.py
spring_equations/hooke_law.py
spring_plots/__init__.py
spring_plots/plot_energy.py
spring_plots/plot_force.py
spring_plots/plot_harmonic.py
spring_plots/plot_hooke.py
spring_force-0.0.1.dist-info/METADATA
spring_force-0.0.1.dist-info/WHEEL
spring_force-0.0.1.dist-info/top_level.txt
spring_force-0.0.1.dist-info/RECORD
