Metadata-Version: 2.1
Name: spring-force
Version: 0.0.1
Summary: A tool for generating solutions and plots for Hooke Law and Harmonic Oscillation
Home-page: https://github.com/tiemi/image-processing-package
Author: Egleidson Frederik
License: UNKNOWN
Platform: UNKNOWN
Requires-Python: >=3.5
Requires-Dist: matplotlib
